dbnomics/__init__.py
dbnomics/py.typed
dbnomics-1.2.6.dist-info/METADATA
dbnomics-1.2.6.dist-info/WHEEL
dbnomics-1.2.6.dist-info/licenses/LICENSE
dbnomics-1.2.6.dist-info/RECORD
