Metadata-Version: 2.4
Name: dbnomics
Version: 1.2.6
Summary: DBnomics Python client
Project-URL: Homepage, https://git.nomics.world/dbnomics/dbnomics-python-client
Project-URL: Bug Tracker, https://git.nomics.world/dbnomics/dbnomics-python-client/-/issues
Author-email: Christophe Benz <christophe.benz@nomics.world>
License:                     GNU AFFERO GENERAL PUBLIC LICENSE
License-File: LICENSE
Classifier: License :: OSI Approved :: GNU Affero General Public License v3 or later (AGPLv3+)
Classifier: Operating System :: OS Independent
Classifier: Programming Language :: Python :: 3
Requires-Python: >=3.11
Requires-Dist: pandas>=2.2.3
Requires-Dist: requests>=2.32.3
Requires-Dist: tenacity>=9.0.0
